setup.py
few_dists/Binomialdistribution.py
few_dists/Gaussiandistribution.py
few_dists/Generaldistribution.py
few_dists/__init__.py
few_dists.egg-info/PKG-INFO
few_dists.egg-info/SOURCES.txt
few_dists.egg-info/dependency_links.txt
few_dists.egg-info/not-zip-safe
few_dists.egg-info/top_level.txt