Metadata-Version: 1.0
Name: few-dists
Version: 1.0
Summary: Gaussian and Binomial distributions
Home-page: UNKNOWN
Author: Chandrama Naha
Author-email: chandrama.naha@gmail.com
License: UNKNOWN
Platform: UNKNOWN
